README.md
setup.py
etl_tools/__init__.py
etl_tools/config.py
etl_tools/create_attributes_table.py
etl_tools/schema_check.py
etl_tools/schema_copying.py
etl_tools/utils.py
etl_tools/create_time_dimensions/__init__.py
etl_tools/initialize_utils/__init__.py
etl_tools/load_euro_exchange_rates/__init__.py
etl_tools/load_euro_exchange_rates/load_exchange_rate.py
mara_etl_tools.egg-info/PKG-INFO
mara_etl_tools.egg-info/SOURCES.txt
mara_etl_tools.egg-info/dependency_links.txt
mara_etl_tools.egg-info/requires.txt
mara_etl_tools.egg-info/top_level.txt