Metadata-Version: 2.1
Name: mara-etl-tools
Version: 4.0.0
Summary: Utilities for creating ETL pipelines with mara
Home-page: https://github.com/mara/mara-etl-tools
Author: Mara contributors
License: MIT
Platform: UNKNOWN
Requires-Python: >=3.6
